<annotation>
	<folder>aloo_paratha</folder>
	<filename>10000105.jpg</filename>
	<path>/home/anupam/downloads/aloo_paratha/10000105.jpg</path>
	<source>
		<database>Unknown</database>
	</source>
	<size>
		<width>900</width>
		<height>600</height>
		<depth>3</depth>
	</size>
	<segmented>0</segmented>
	<object>
		<name>aloo_paratha</name>
		<pose>Unspecified</pose>
		<truncated>0</truncated>
		<difficult>0</difficult>
		<bndbox>
			<xmin>74</xmin>
			<ymin>46</ymin>
			<xmax>756</xmax>
			<ymax>574</ymax>
		</bndbox>
	</object>
</annotation>
