<annotation>
	<folder>aloo_paratha</folder>
	<filename>10000110.jpg</filename>
	<path>/home/anupam/downloads/aloo_paratha/10000110.jpg</path>
	<source>
		<database>Unknown</database>
	</source>
	<size>
		<width>1600</width>
		<height>1066</height>
		<depth>3</depth>
	</size>
	<segmented>0</segmented>
	<object>
		<name>aloo_paratha</name>
		<pose>Unspecified</pose>
		<truncated>0</truncated>
		<difficult>0</difficult>
		<bndbox>
			<xmin>230</xmin>
			<ymin>328</ymin>
			<xmax>1091</xmax>
			<ymax>871</ymax>
		</bndbox>
	</object>
</annotation>
